<?xml version="1.0" encoding="UTF-8"?>
<con:operation isOneWay="false" action="http://www.yota.ru/vox/services/b2b/wsdl/ClientDocumentManagement/RemoveDocument" name="removeDocument" bindingOperationName="removeDocument" type="Request-Response" outputName="RemoveDocumentOut" inputName="RemoveDocumentIn" receivesAttachments="false" sendsAttachments="false" anonymous="optional" id="3c9168dc-cddc-496b-8427-1a286a842829" xmlns:xsi="http://www.w3.org/2001/XMLSchema-instance" xmlns:con="http://eviware.com/soapui/config"><con:settings><con:setting id="3c9168dc-cddc-496b-8427-1a286a842829fileName">removeDocument</con:setting></con:settings><con:call name="Request 1" id="54888e86-a525-432e-86e3-33c8070471f0"><con:settings/><con:encoding>UTF-8</con:encoding><con:endpoint>http://b2btst-corpjs-cdm.g4lab.com:8080/cdm-web/ClientDocumentManagementEndpoint</con:endpoint><con:request><![CDATA[<soapenv:Envelope xmlns:soapenv="http://schemas.xmlsoap.org/soap/envelope/" xmlns:doc="http://www.yota.ru/vox/b2b/services/document">\r
   <soapenv:Header/>\r
   <soapenv:Body>\r
      <doc:RemoveDocumentRequest>\r
         <docId>?</docId>\r
      </doc:RemoveDocumentRequest>\r
   </soapenv:Body>\r
</soapenv:Envelope>]]></con:request><con:credentials><con:selectedAuthProfile>No Authorization</con:selectedAuthProfile><con:authType>No Authorization</con:authType></con:credentials><con:jmsConfig JMSDeliveryMode="PERSISTENT"/><con:wsaConfig mustUnderstand="NONE" version="200508" action="http://www.yota.ru/vox/services/b2b/wsdl/ClientDocumentManagement/RemoveDocument"/></con:call></con:operation>