<?xml version="1.0" encoding="UTF-8"?>
<con:operation isOneWay="false" action="http://www.yota.ru/vox/services/wsdl/CustomerProduct/AddCommentForAccount" name="AddCommentForAccount" bindingOperationName="AddCommentForAccount" type="Request-Response" outputName="AddCommentForAccountOut" inputName="AddCommentForAccountIn" receivesAttachments="false" sendsAttachments="false" anonymous="optional" id="0f98ed6d-9681-4420-816d-53737103594c" xmlns:xsi="http://www.w3.org/2001/XMLSchema-instance" xmlns:con="http://eviware.com/soapui/config"><con:settings><con:setting id="0f98ed6d-9681-4420-816d-53737103594cfileName">AddCommentForAccount</con:setting></con:settings><con:call name="Request 1" id="deb0671f-dd52-43f5-b565-de70a1b848e5"><con:settings/><con:encoding>UTF-8</con:encoding><con:endpoint>http://10.78.209.200:8382/customer-product-ejb/CustomerProduct/CustomerProductServiceBean</con:endpoint><con:request><![CDATA[<soapenv:Envelope xmlns:soapenv="http://schemas.xmlsoap.org/soap/envelope/" xmlns:cus="http://www.yota.ru/vox/services/customerProduct" xmlns:core="http://www.roox.ru/products/common/core">
   <soapenv:Header/>
   <soapenv:Body>
      <cus:AddCommentForAccountRequest>
         <!--Optional:-->
         <core:extension>
            <!--Zero or more repetitions:-->
            <core:item>?</core:item>
         </core:extension>
         <accountId>?</accountId>
         <comment>?</comment>
      </cus:AddCommentForAccountRequest>
   </soapenv:Body>
</soapenv:Envelope>]]></con:request><con:credentials><con:selectedAuthProfile>No Authorization</con:selectedAuthProfile><con:authType>No Authorization</con:authType></con:credentials><con:jmsConfig JMSDeliveryMode="PERSISTENT"/><con:wsaConfig mustUnderstand="NONE" version="200508" action="http://www.yota.ru/vox/services/wsdl/CustomerProduct/AddCommentForAccount"/></con:call></con:operation>