<?xml version="1.0" encoding="UTF-8"?>
<con:resource name="cyberplat" path="/adapters/cyber-proto/cyberplat" id="c221688a-6e16-4ed0-ab91-182d21fcc1c1" xmlns:xsi="http://www.w3.org/2001/XMLSchema-instance" xmlns:con="http://eviware.com/soapui/config"><con:settings><con:setting id="c221688a-6e16-4ed0-ab91-182d21fcc1c1fileName">cyberplat</con:setting></con:settings><con:parameters><con:parameter><con:name>action</con:name><con:value/><con:style>QUERY</con:style><con:default/></con:parameter><con:parameter><con:name>number</con:name><con:value/><con:style>QUERY</con:style><con:default/></con:parameter><con:parameter><con:name>receipt</con:name><con:value/><con:style>QUERY</con:style><con:default/></con:parameter><con:parameter><con:name>date</con:name><con:value/><con:style>QUERY</con:style><con:default/></con:parameter><con:parameter><con:name>amount</con:name><con:value/><con:style>QUERY</con:style><con:default/></con:parameter><con:parameter><con:name>type</con:name><con:value/><con:style>QUERY</con:style><con:default/></con:parameter></con:parameters><con:method name="cyberplat" id="b5cc86b4-8cce-411b-94c1-eedafd879847" method="GET"><con:settings/><con:parameters/><con:representation type="RESPONSE" id=""><con:mediaType>text/html;charset=Windows-1251</con:mediaType><con:status>200</con:status><con:params/><con:element xsi:nil="true"/><con:description xsi:nil="true"/></con:representation><con:representation type="RESPONSE" id=""><con:mediaType>text/html</con:mediaType><con:status/><con:params/><con:element xsi:nil="true"/><con:description xsi:nil="true"/></con:representation><con:representation type="RESPONSE" id=""><con:mediaType/><con:status>0</con:status><con:params/><con:element xsi:nil="true"/><con:description xsi:nil="true"/></con:representation><con:representation type="RESPONSE" id=""><con:mediaType/><con:status>0</con:status><con:params/><con:element xsi:nil="true"/><con:description xsi:nil="true"/></con:representation><con:representation type="RESPONSE" id=""><con:mediaType/><con:status>0</con:status><con:params/><con:element xsi:nil="true"/><con:description xsi:nil="true"/></con:representation><con:representation type="RESPONSE" id=""><con:mediaType/><con:status>0</con:status><con:params/><con:element xsi:nil="true"/><con:description xsi:nil="true"/></con:representation><con:representation type="RESPONSE" id=""><con:mediaType/><con:status>0</con:status><con:params/><con:element xsi:nil="true"/><con:description xsi:nil="true"/></con:representation><con:representation type="RESPONSE" id=""><con:mediaType/><con:status>0</con:status><con:params/><con:element xsi:nil="true"/><con:description xsi:nil="true"/></con:representation><con:representation type="RESPONSE" id=""><con:mediaType/><con:status>0</con:status><con:params/><con:element xsi:nil="true"/><con:description xsi:nil="true"/></con:representation><con:representation type="RESPONSE" id=""><con:mediaType/><con:status>0</con:status><con:params/><con:element xsi:nil="true"/><con:description xsi:nil="true"/></con:representation><con:representation type="RESPONSE" id=""><con:mediaType/><con:status>0</con:status><con:params/><con:element xsi:nil="true"/><con:description xsi:nil="true"/></con:representation><con:representation type="RESPONSE" id=""><con:mediaType/><con:status>0</con:status><con:params/><con:element xsi:nil="true"/><con:description xsi:nil="true"/></con:representation><con:representation type="RESPONSE" id=""><con:mediaType/><con:status>0</con:status><con:params/><con:element xsi:nil="true"/><con:description xsi:nil="true"/></con:representation><con:representation type="RESPONSE" id=""><con:mediaType/><con:status>0</con:status><con:params/><con:element xsi:nil="true"/><con:description xsi:nil="true"/></con:representation><con:representation type="RESPONSE" id=""><con:mediaType/><con:status>0</con:status><con:params/><con:element xsi:nil="true"/><con:description xsi:nil="true"/></con:representation><con:representation type="RESPONSE" id=""><con:mediaType/><con:status>0</con:status><con:params/><con:element xsi:nil="true"/><con:description xsi:nil="true"/></con:representation><con:representation type="RESPONSE" id=""><con:mediaType/><con:status>0</con:status><con:params/><con:element xsi:nil="true"/><con:description xsi:nil="true"/></con:representation><con:representation type="RESPONSE" id=""><con:mediaType/><con:status>0</con:status><con:params/><con:element xsi:nil="true"/><con:description xsi:nil="true"/></con:representation><con:request name="Request 1" id="95e6010e-e18d-4cb5-8881-fde27173427c" mediaType="application/json"><con:settings/><con:endpoint>https://</con:endpoint><con:request/><con:credentials><con:selectedAuthProfile>No Authorization</con:selectedAuthProfile><con:authType>No Authorization</con:authType></con:credentials><con:jmsConfig JMSDeliveryMode="PERSISTENT"/><con:jmsPropertyConfig/><con:parameters/></con:request></con:method></con:resource>