<?xml version="1.0" encoding="UTF-8"?>
<con:operation isOneWay="false" action="http://www.yota.ru/vox/services/b2b/wsdl/PortalUserManagement/GetPasswordRecallURL" name="getPasswordRecallURL" bindingOperationName="getPasswordRecallURL" type="Request-Response" outputName="getPasswordRecallURLResponse" inputName="getPasswordRecallURL" receivesAttachments="false" sendsAttachments="false" anonymous="optional" id="76ea5a1b-4784-4819-abcb-72823ac0b3b4" xmlns:xsi="http://www.w3.org/2001/XMLSchema-instance" xmlns:con="http://eviware.com/soapui/config"><con:settings><con:setting id="76ea5a1b-4784-4819-abcb-72823ac0b3b4fileName">getPasswordRecallURL</con:setting></con:settings><con:call name="Request 1" id="ede0b2a9-02cc-41c0-bcc8-d07e61ed86e3"><con:settings><con:setting id="com.eviware.soapui.impl.wsdl.WsdlRequest@request-headers">&lt;xml-fragment/></con:setting></con:settings><con:encoding>UTF-8</con:encoding><con:endpoint>http://b2bload-ps1.g4lab.com:8080/user-service/services/PortalUserManagement</con:endpoint><con:request><![CDATA[<soapenv:Envelope xmlns:soapenv="http://schemas.xmlsoap.org/soap/envelope/" xmlns:por="http://www.yota.ru/vox/b2b/services/portal">
   <soapenv:Header/>
   <soapenv:Body>
      <por:GetPasswordRecallURLRequest>
         <customerId>4de83b8c43c842d6a42ff61a0f85d9eb</customerId>
      </por:GetPasswordRecallURLRequest>
   </soapenv:Body>
</soapenv:Envelope>]]></con:request><con:credentials><con:selectedAuthProfile>Basic</con:selectedAuthProfile><con:authType>Global HTTP Settings</con:authType></con:credentials><con:jmsConfig JMSDeliveryMode="PERSISTENT"/><con:jmsPropertyConfig/><con:wsaConfig mustUnderstand="NONE" version="200508" action="http://www.yota.ru/vox/services/b2b/wsdl/PortalUserManagement/GetPasswordRecallURL"/><con:wsrmConfig version="1.2"/></con:call></con:operation>